ezargs/__init__.py
ezargs/parser.py
ezargs-0.0.6.dist-info/METADATA
ezargs-0.0.6.dist-info/WHEEL
ezargs-0.0.6.dist-info/licenses/LICENSE
ezargs-0.0.6.dist-info/RECORD
