Metadata-Version: 2.1
Name: ezargs
Version: 0.0.6
Summary: zero-setup dynamic python command line argument parsing
Project-URL: Homepage, https://github.com/m12t/ezargs
Project-URL: Bug Tracker, https://github.com/m12t/ezargs/issues
Author-email: Michael <m12tbucket@gmail.com>
License-File: LICENSE
Classifier: License :: OSI Approved :: MIT License
Classifier: Operating System :: OS Independent
Classifier: Programming Language :: Python :: 3
Requires-Python: >=3.7
